tkmfly/__init__.py
tkmfly/_mkwidgets/Aclock.tcl
tkmfly/_mkwidgets/Calendar.tcl
tkmfly/_mkwidgets/Combobox.tcl
tkmfly/_mkwidgets/Document.tcl
tkmfly/_mkwidgets/Gridcontrol.tcl
tkmfly/_mkwidgets/Ibutton.tcl
tkmfly/_mkwidgets/Iconbox.tcl
tkmfly/_mkwidgets/Listcontrol.tcl
tkmfly/_mkwidgets/metawidget.tcl
tkmfly/_mkwidgets/mkWidgets13.htm
tkmfly/_mkwidgets/mkWidgetsCol13.htm
tkmfly/_mkwidgets/Pane.tcl
tkmfly/_mkwidgets/pkgIndex.tcl
tkmfly/_mkwidgets/Progressbar.tcl
tkmfly/_mkwidgets/ReadMe.txt
tkmfly/_mkwidgets/Scrollbox.tcl
tkmfly/_mkwidgets/Spinentry.tcl
tkmfly/_mkwidgets/Statusbar.tcl
tkmfly/_mkwidgets/Tabcontrol.tcl
tkmfly/_mkwidgets/Textframe.tcl
tkmfly/_mkwidgets/Toolbar.tcl
tkmfly/_mkwidgets/Tooltip.tcl
tkmfly/_mkwidgets/Treecontrol.tcl
tkmfly/_mkwidgets/Window.tcl
tkmfly/core.py
tkmfly/datefield/__init__.py
tkmfly/datefield/pkgIndex.py
tkmfly/history/__init__.py
tkmfly/history/pkgIndex.py
tkmfly/mdi.py
tkmfly/mkwidgets/__init__.py
tkmfly/mkwidgets/calendar.py
tkmfly/mkwidgets/document.py
tkmfly/mkwidgets/toolbar.py
tkmfly/mkwidgets/window.py
tkmfly/notifywindow/__init__.py
tkmfly/notifywindow/pkgIndex.py
tkmfly/tkmdi/__init__.py
tkmfly/tkmdi/Icons/activehorztab.gif
tkmfly/tkmdi/Icons/activeverttab.gif
tkmfly/tkmdi/Icons/backwards.gif
tkmfly/tkmdi/Icons/ballstick.gif
tkmfly/tkmdi/Icons/ballstick2.gif
tkmfly/tkmdi/Icons/circle.gif
tkmfly/tkmdi/Icons/close.gif
tkmfly/tkmdi/Icons/corner.gif
tkmfly/tkmdi/Icons/cut.gif
tkmfly/tkmdi/Icons/down.gif
tkmfly/tkmdi/Icons/draw.gif
tkmfly/tkmdi/Icons/end.gif
tkmfly/tkmdi/Icons/folder.gif
tkmfly/tkmdi/Icons/horzsep.gif
tkmfly/tkmdi/Icons/horztab.gif
tkmfly/tkmdi/Icons/info.gif
tkmfly/tkmdi/Icons/left.gif
tkmfly/tkmdi/Icons/maximize.gif
tkmfly/tkmdi/Icons/minimize.gif
tkmfly/tkmdi/Icons/minusnode.gif
tkmfly/tkmdi/Icons/new.gif
tkmfly/tkmdi/Icons/nothing.gif
tkmfly/tkmdi/Icons/open.gif
tkmfly/tkmdi/Icons/openfolder.gif
tkmfly/tkmdi/Icons/pause.gif
tkmfly/tkmdi/Icons/play.gif
tkmfly/tkmdi/Icons/plusnode.gif
tkmfly-0.1.0b4.dist-info/METADATA
tkmfly-0.1.0b4.dist-info/WHEEL
tkmfly-0.1.0b4.dist-info/RECORD
