Metadata-Version: 2.1
Name: tkmfly
Version: 0.1.0b4
Summary: 
Author: XiangQinxi
Author-email: 1379773753@qq.com
Requires-Python: >=3.7,<4.0
Classifier: Programming Language :: Python :: 3
Classifier: Programming Language :: Python :: 3.7
Classifier: Programming Language :: Python :: 3.8
Classifier: Programming Language :: Python :: 3.9
Classifier: Programming Language :: Python :: 3.10
Classifier: Programming Language :: Python :: 3.11
Requires-Dist: pmw (>=2.1.1,<3.0.0)
